[
  {
    "mid": 13433,
    "is_readed": 0,
    "title": "long time no see",
    "content": "Wolf bespoke man braid hoodie, skateboard offal asymmetrical trajectory in consumer product funding in coming months.",
    "from_username": "HUYITIAN",
    "time": 1517558543,
    "header": "../../../../assets/images/1.jpg"
  },
  {
    "mid": 13434,
    "is_readed": 1,
    "title": "long time no see",
    "content": "Wolf bespoke man braid hoodie, skateboard offal asymmetrical trajectory in consumer product funding in coming months.",
    "from_username": "Vision Wei",
    "time": 1507558543,
    "header": "../../../../assets/images/2.jpg"
  },
  {
    "mid": 13435,
    "is_readed": 0,
    "title": "long time no see",
    "content": "Wolf bespoke man braid hoodie, skateboard offal asymmetrical trajectory in consumer product funding in coming months.",
    "from_username": "Suzy",
    "time": 1517448543,
    "header": "../../../../assets/images/3.jpg"
  },
  {
    "mid": 13436,
    "is_readed": 0,
    "title": "long time no see",
    "content": "Wolf bespoke man braid hoodie, skateboard offal asymmetrical trajectory in consumer product funding in coming months.",
    "from_username": "SHENYUE",
    "time": 1517558543,
    "header": "../../../../assets/images/1.jpg"
  }
]
